snortparser/__init__.py
snortparser/parser.py
snortparser-0.1b3.dist-info/DESCRIPTION.rst
snortparser-0.1b3.dist-info/METADATA
snortparser-0.1b3.dist-info/RECORD
snortparser-0.1b3.dist-info/WHEEL
snortparser-0.1b3.dist-info/metadata.json
snortparser-0.1b3.dist-info/top_level.txt
